<?xml version="1.0" encoding="utf-8"?>
<DT15 Behavior="Searching" Collision="0" Doubtful="0" Length="36" Status="Alive">
   <Event Type="Stopped">
      <pose>[1154 1758;1153 1758;1152 1757;1151 1756;1150 1755;1149 1755;1148 1755;1147 1754;1146 1753;1145 1752;1144 1751;1143 1750;1143 1749;1143 1748;1143 1747;1144 1746;1144 1745;1145 1744;1145 1743;1145 1742;1145 1741;1145 1740;1144 1739;1143 1738;1142 1737;1141 1736;1140 1735;1139 1734;1138 1733;1137 1732]</pose>
      <pose>[1154 1760;1154 1759;1154 1758;1153 1757;1152 1756;1151 1756;1150 1755;1149 1755;1148 1755;1147 1754;1146 1753;1145 1752;1144 1751;1143 1750;1143 1749;1143 1748;1143 1747;1144 1746;1144 1745;1145 1744;1145 1743;1145 1742;1145 1741;1145 1740;1144 1739;1143 1738;1142 1737;1141 1736;1140 1735;1139 1735;1138 1734;1137 1733]</pose>
   </Event>
   <Event Type="Forward">
      <pose>[1154 1758;1153 1758;1152 1757;1151 1756;1150 1755;1149 1755;1148 1754;1147 1754;1146 1753;1145 1752;1144 1751;1143 1750;1143 1749;1143 1748;1143 1747;1144 1746;1144 1745;1144 1744;1144 1743;1145 1742;1145 1741;1145 1740;1144 1739;1143 1738;1142 1737;1141 1736;1140 1735;1140 1734;1139 1733;1139 1732;1139 1731;1140 1730]</pose>
   </Event>
   <Event Type="Backwards">
      <pose>[1153 1756;1152 1756;1151 1756;1150 1755;1149 1755;1148 1755;1147 1754;1146 1753;1145 1752;1144 1751;1144 1750;1144 1749;1144 1748;1144 1747;1144 1746;1144 1745;1144 1744;1144 1743;1145 1742;1145 1741;1144 1740;1144 1739;1143 1738;1142 1737;1141 1736;1140 1735;1139 1734;1139 1733;1139 1732;1139 1731;1140 1730;1140 1729;1141 1728]</pose>
   </Event>
   <Event Type="Stopped">
      <pose>[1154 1758;1153 1757;1152 1756;1151 1756;1150 1755;1149 1755;1148 1754;1147 1754;1146 1753;1145 1752;1144 1751;1143 1750;1143 1749;1143 1748;1143 1747;1144 1746;1144 1745;1144 1744;1144 1743;1144 1742;1144 1741;1144 1740;1144 1739;1143 1738;1143 1737;1142 1736;1141 1735;1141 1734;1140 1733;1140 1732;1140 1731]</pose>
   </Event>
   <Event Type="Forward">
      <pose>[1154 1758;1153 1757;1152 1756;1151 1756;1150 1755;1149 1755;1148 1755;1147 1754;1146 1753;1145 1753;1144 1752;1143 1751;1143 1750;1143 1749;1143 1748;1144 1747;1144 1746;1144 1745;1144 1744;1145 1743;1145 1742;1145 1741;1144 1740;1144 1739;1143 1738;1143 1737;1143 1736;1142 1735;1141 1734;1140 1733;1139 1732;1138 1732;1137 1732;1136 1732;1135 1732]</pose>
   </Event>
   <Event Type="Stopped">
      <pose>[1151 1755;1150 1755;1149 1755;1148 1755;1147 1754;1146 1753;1145 1753;1144 1752;1143 1751;1143 1750;1143 1749;1143 1748;1144 1747;1144 1746;1144 1745;1144 1744;1145 1743;1145 1742;1144 1741;1144 1740;1144 1739;1144 1738;1143 1737;1143 1736;1142 1735;1141 1734;1140 1733;1139 1733;1138 1733;1137 1733;1136 1733;1135 1733;1134 1733;1133 1733;1132 1733;1131 1733]</pose>
   </Event>
   <Event Type="Forward">
      <pose>[1149 1755;1148 1755;1147 1755;1146 1754;1145 1753;1144 1752;1144 1751;1144 1750;1143 1749;1143 1748;1143 1747;1144 1746;1144 1745;1144 1744;1145 1743;1145 1742;1145 1741;1145 1740;1144 1739;1144 1738;1143 1737;1142 1736;1141 1735;1140 1734;1139 1733;1138 1733;1137 1733;1136 1733;1135 1733;1134 1733;1133 1733;1132 1733;1131 1733;1130 1732;1129 1731;1128 1730]</pose>
   </Event>
   <Event Type="Stopped">
      <pose>[1143 1749;1143 1748;1143 1747;1144 1746;1144 1745;1144 1744;1144 1743;1145 1742;1145 1741;1144 1740;1144 1739;1144 1738;1143 1737;1142 1736;1141 1735;1140 1735;1139 1734;1138 1734;1137 1734;1136 1734;1135 1734;1134 1734;1133 1734;1132 1733;1131 1732;1131 1731;1130 1730;1130 1729;1129 1728;1128 1727;1127 1726]</pose>
   </Event>
   <Event Type="Forward">
      <pose>[1143 1747;1143 1746;1144 1745;1144 1744;1144 1743;1144 1742;1145 1741;1145 1740;1145 1739;1144 1738;1143 1737;1142 1736;1141 1736;1140 1735;1139 1735;1138 1735;1137 1735;1136 1735;1135 1735;1134 1734;1133 1733;1132 1732;1131 1731;1131 1730;1130 1729;1129 1728;1128 1727;1127 1726;1126 1726;1125 1726;1124 1726;1123 1727;1122 1728]</pose>
      <pose>[1145 1739;1144 1738;1143 1737;1142 1737;1141 1736;1140 1736;1139 1736;1138 1736;1137 1735;1136 1735;1135 1735;1134 1734;1133 1733;1132 1732;1132 1731;1131 1730;1130 1729;1129 1728;1128 1727;1127 1726;1126 1726;1125 1726;1124 1726;1123 1727;1122 1727;1121 1728;1120 1728;1119 1729;1118 1729;1117 1729;1116 1729]</pose>
      <pose>[1142 1736;1141 1736;1140 1736;1139 1736;1138 1736;1137 1736;1136 1735;1135 1734;1134 1733;1133 1732;1132 1731;1131 1730;1131 1729;1130 1728;1129 1727;1128 1727;1127 1726;1126 1726;1125 1726;1124 1726;1123 1727;1122 1728;1121 1728;1120 1729;1119 1729;1118 1729;1117 1729;1116 1728;1115 1727;1114 1726;1114 1725;1114 1724;1114 1723;1114 1722;1114 1721;1114 1720]</pose>
   </Event>
   <Event Type="Stopped">
      <pose>[1133 1732;1132 1731;1132 1730;1131 1729;1130 1728;1129 1727;1128 1727;1127 1727;1126 1727;1125 1727;1124 1727;1123 1728;1122 1728;1121 1729;1120 1729;1119 1729;1118 1729;1117 1728;1116 1727;1115 1726;1115 1725;1114 1724;1114 1723;1114 1722;1114 1721;1113 1720;1112 1719;1111 1718;1110 1718;1109 1718]</pose>
      <pose>[1133 1730;1132 1729;1131 1728;1130 1728;1129 1728;1128 1727;1127 1727;1126 1727;1125 1727;1124 1727;1123 1727;1122 1728;1121 1729;1120 1729;1119 1729;1118 1729;1117 1728;1116 1727;1115 1726;1115 1725;1114 1724;1114 1723;1114 1722;1114 1721;1113 1720;1112 1719;1111 1719;1110 1718;1109 1718;1108 1717;1107 1717;1106 1717;1105 1717;1104 1718;1103 1718;1102 1718]</pose>
   </Event>
   <Event Type="Forward">
      <pose>[1132 1729;1131 1728;1130 1727;1129 1727;1128 1727;1127 1727;1126 1727;1125 1727;1124 1728;1123 1728;1122 1728;1121 1729;1120 1729;1119 1729;1118 1728;1117 1727;1116 1726;1115 1725;1115 1724;1114 1723;1114 1722;1114 1721;1113 1720;1112 1719;1111 1718;1110 1718;1109 1718;1108 1718;1107 1718;1106 1719;1105 1719;1104 1718;1103 1718;1102 1717;1102 1716;1101 1715]</pose>
      <pose>[1126 1727;1125 1727;1124 1728;1123 1728;1122 1729;1121 1729;1120 1729;1119 1729;1118 1728;1117 1727;1116 1726;1115 1725;1115 1724;1115 1723;1115 1722;1114 1721;1113 1720;1112 1719;1111 1719;1110 1718;1109 1718;1108 1718;1107 1718;1106 1719;1105 1719;1104 1718;1103 1717;1102 1716;1101 1715;1101 1714;1100 1713;1100 1712]</pose>
      <pose>[1123 1729;1122 1729;1121 1729;1120 1729;1119 1728;1118 1727;1117 1726;1116 1725;1115 1724;1115 1723;1114 1722;1113 1721;1112 1720;1111 1719;1110 1719;1109 1719;1108 1719;1107 1719;1106 1719;1105 1718;1104 1717;1103 1716;1102 1715;1101 1714;1101 1713;1100 1712;1099 1711;1098 1710;1097 1709;1096 1709;1095 1709;1094 1709]</pose>
      <pose>[1117 1725;1116 1725;1115 1724;1115 1723;1115 1722;1114 1721;1113 1720;1112 1720;1111 1720;1110 1719;1109 1719;1108 1719;1107 1719;1106 1718;1105 1717;1104 1716;1103 1715;1102 1714;1102 1713;1101 1712;1100 1711;1099 1710;1098 1710;1097 1709;1096 1709;1095 1709;1094 1710;1093 1710;1092 1710;1091 1710;1090 1709;1089 1708;1088 1707]</pose>
      <pose>[1116 1722;1115 1721;1114 1721;1113 1720;1112 1720;1111 1720;1110 1720;1109 1719;1108 1719;1107 1719;1106 1718;1105 1717;1104 1716;1104 1715;1103 1714;1102 1713;1101 1712;1100 1711;1099 1710;1098 1710;1097 1710;1096 1710;1095 1710;1094 1710;1093 1710;1092 1710;1091 1710;1090 1709;1089 1708;1088 1707;1088 1706;1088 1705;1088 1704]</pose>
      <pose>[1110 1719;1109 1719;1108 1719;1107 1719;1106 1718;1105 1717;1105 1716;1104 1715;1103 1714;1102 1713;1101 1712;1100 1711;1099 1711;1098 1711;1097 1711;1096 1711;1095 1711;1094 1711;1093 1710;1092 1710;1091 1709;1090 1708;1089 1707;1089 1706;1088 1705;1088 1704;1088 1703;1087 1702;1086 1701;1085 1701;1084 1701;1083 1701;1082 1700;1081 1700]</pose>
   </Event>
   <Event Type="Backwards">
      <pose>[1106 1716;1105 1716;1104 1715;1103 1714;1102 1713;1101 1712;1100 1712;1099 1712;1098 1712;1097 1712;1096 1712;1095 1711;1094 1711;1093 1711;1092 1710;1091 1709;1090 1708;1090 1707;1089 1706;1089 1705;1089 1704;1088 1703;1087 1702;1086 1701;1085 1701;1084 1701;1083 1701;1082 1701;1081 1701;1080 1701;1079 1702;1078 1702;1077 1702;1076 1701;1075 1701]</pose>
   </Event>
   <Event Type="Forward">
      <pose>[1104 1711;1103 1711;1102 1712;1101 1712;1100 1712;1099 1712;1098 1712;1097 1712;1096 1712;1095 1712;1094 1711;1093 1710;1092 1709;1091 1708;1091 1707;1090 1706;1089 1705;1088 1704;1087 1703;1086 1702;1085 1702;1084 1701;1083 1701;1082 1702;1081 1702;1080 1702;1079 1702;1078 1702;1077 1701;1076 1700;1075 1699;1075 1698;1074 1697]</pose>
      <pose>[1099 1711;1098 1711;1097 1711;1096 1712;1095 1712;1094 1711;1093 1711;1092 1710;1091 1709;1091 1708;1091 1707;1090 1706;1090 1705;1089 1704;1088 1703;1087 1702;1086 1702;1085 1702;1084 1702;1083 1702;1082 1702;1081 1702;1080 1702;1079 1702;1078 1701;1077 1700;1076 1699;1075 1698;1074 1697;1073 1696;1072 1695;1071 1695;1070 1695;1069 1694]</pose>
      <pose>[1091 1708;1091 1707;1090 1706;1090 1705;1089 1704;1088 1703;1087 1703;1086 1703;1085 1703;1084 1703;1083 1703;1082 1703;1081 1703;1080 1703;1079 1702;1078 1701;1077 1700;1076 1699;1075 1698;1074 1697;1073 1696;1072 1695;1071 1695;1070 1695;1069 1695;1068 1695;1067 1695;1066 1696;1065 1696;1064 1697;1063 1698]</pose>
      <pose>[1091 1704;1090 1704;1089 1704;1088 1704;1087 1704;1086 1704;1085 1703;1084 1703;1083 1703;1082 1703;1081 1703;1080 1702;1079 1701;1078 1700;1077 1699;1076 1698;1075 1697;1074 1696;1073 1696;1072 1696;1071 1696;1070 1696;1069 1696;1068 1696;1067 1696;1066 1697;1065 1697;1064 1697;1063 1697;1062 1696;1061 1695;1060 1694;1060 1693;1060 1692;1060 1691]</pose>
      <pose>[1085 1703;1084 1703;1083 1703;1082 1703;1081 1703;1080 1702;1079 1701;1078 1700;1077 1699;1076 1698;1075 1697;1074 1696;1073 1696;1072 1696;1071 1696;1070 1696;1069 1697;1068 1697;1067 1697;1066 1697;1065 1697;1064 1697;1063 1697;1062 1696;1061 1695;1061 1694;1060 1693;1060 1692;1060 1691;1059 1690;1059 1689;1058 1688;1057 1688;1056 1688;1055 1687]</pose>
      <pose>[1080 1700;1079 1699;1078 1699;1077 1698;1076 1698;1075 1697;1074 1697;1073 1697;1072 1697;1071 1697;1070 1697;1069 1697;1068 1698;1067 1698;1066 1698;1065 1698;1064 1697;1063 1696;1062 1695;1062 1694;1061 1693;1061 1692;1060 1691;1059 1690;1058 1689;1057 1688;1056 1688;1055 1688;1054 1688;1053 1688;1052 1688;1051 1688;1050 1689;1049 1689;1048 1689;1047 1689]</pose>
   </Event>
   <Event Type="Stopped">
      <pose>[1074 1697;1073 1697;1072 1697;1071 1697;1070 1697;1069 1698;1068 1698;1067 1698;1066 1698;1065 1697;1064 1696;1063 1695;1062 1694;1061 1693;1061 1692;1060 1691;1059 1690;1058 1689;1057 1688;1056 1688;1055 1688;1054 1688;1053 1689;1052 1689;1051 1689;1050 1689;1049 1689;1048 1689;1047 1688;1046 1687;1045 1686]</pose>
   </Event>
   <Event Type="Forward">
      <pose>[1071 1697;1070 1697;1069 1698;1068 1698;1067 1697;1066 1697;1065 1697;1064 1696;1063 1695;1062 1694;1061 1693;1061 1692;1060 1691;1059 1690;1058 1689;1057 1689;1056 1689;1055 1689;1054 1689;1053 1689;1052 1689;1051 1690;1050 1690;1049 1689;1048 1689;1047 1688;1046 1687;1046 1686;1045 1685]</pose>
      <pose>[1067 1697;1066 1697;1065 1697;1064 1696;1063 1695;1062 1694;1061 1693;1060 1692;1059 1691;1058 1690;1057 1690;1056 1690;1055 1690;1054 1690;1053 1690;1052 1690;1051 1690;1050 1689;1049 1688;1048 1687;1047 1686;1047 1685;1046 1684;1045 1683;1044 1682;1043 1681;1042 1681;1041 1681;1040 1681]</pose>
   </Event>
   <Model>
      <Resize>3</Resize>
      <Weight>[1.13;1.65;1.65;1.5;1.73;1.89;2.41;2.77;3.02;3.3;3.36;3.4;3.55;3.7;3.52;3.61;3.89;4;3.87;3.9;3.72;3.53;3.59;3.41;3.35;3.49;3.8;3.83;3.91;3.67;3.44;3.56;3.5;3.65;3.78;3.4;3.52;3.44;3.45;3.15;3.17;3.16;3.72;3.72;3.88;4.03;3.8;3.69;3.45;3.29;3.25;3.4;3.4;3.42;3.49;3.45;3.45;3.56;3.73;3.78;3.75;3.74;3.83;3.83;3.98;3.47;3.44;3.67;3.85;3.85;3.96;4.13;3.93;3.6;3.42;3.34;3.06;3.17;2.89;3.19;3.12;3.11;3.09;3.24;3.77;4.05;4.1;3.83;3.7;3.49;3.13;3.2;3.03;2.69;2.75;2.57;2.68;2.66;2.53;2.05;2;2]</Weight>
      <Colors>[40.09;38.48;37.37;34.17;30.16;28.57;24.74;22.88;21.53;21.34;21.28;21.1;20.48;19.55;19.29;19.11;18.29;17.91;17.54;16.73;16.65;17.11;17.05;17.11;16.81;17.09;16.29;16.41;15.7;15.57;16.12;16.48;16.98;16.64;16.33;16.18;16.49;17.21;17.45;17.76;16.36;16.41;15.48;15.45;16.56;16.56;16.53;16.44;16.47;17.16;16.76;16.28;15.7;15.39;15.47;15.79;15.59;14.94;14.64;14.33;15.12;15.06;15.31;15.64;14.94;15.17;14.82;14.7;15.22;16.17;16.64;16.67;16.79;17.54;18.11;19.1;20.82;21.98;24.91;25.15;24.93;24.28;23.32;22.87;23.26;23.83;24.31;24.29;24.72;25.16;26.81;25.96;25.91;26.67;26.56;27.7;28.6;30.23;32.44;35;36.74;38.2]</Colors>
   </Model>
</DT15>